kaalka/__init__.py
kaalka/file_encryptor.py
kaalka/file_weave.py
kaalka/kaalka.py
kaalka/ledger.py
kaalka/time_protocol.py
kaalka/tests/__init__.py
kaalka/tests/test_cli.py
kaalka/tests/test_file_weave.py
kaalka/tests/test_kaalka_legacy.py
kaalka/tests/test_time_protocol.py
kaalkaNTP/__init__.py
kaalkaNTP/kaalkaNTP.py
kaalkaNTP/packet.py
kaalka-5.0.0.dist-info/LICENSE
kaalka-5.0.0.dist-info/METADATA
kaalka-5.0.0.dist-info/WHEEL
kaalka-5.0.0.dist-info/entry_points.txt
kaalka-5.0.0.dist-info/top_level.txt
kaalka-5.0.0.dist-info/RECORD
