Metadata-Version: 2.1
Name: kaalka
Version: 5.0.0
Summary: Kaalka: Production-ready time-based encryption library for Python
Home-page: https://github.com/PIYUSH-MISHRA-00/Kaalka-Encryption-Algorithm/tree/python
Author: PIYUSH-MISHRA-00
Author-email: piyushmishra.professional@gmail.com
License: Custom
License-File: LICENSE
Requires-Dist: ntplib
